mblt_model_zoo/__init__.py
mblt_model_zoo/cli/__init__.py
mblt_model_zoo/cli/__main__.py
mblt_model_zoo/cli/main.py
mblt_model_zoo/cli/tps.py
mblt_model_zoo/transformers/__init__.py
mblt_model_zoo/transformers/large_language_model/__init__.py
mblt_model_zoo/transformers/large_language_model/bert.py
mblt_model_zoo/transformers/large_language_model/cohere2.py
mblt_model_zoo/transformers/large_language_model/exaone.py
mblt_model_zoo/transformers/large_language_model/exaone4.py
mblt_model_zoo/transformers/large_language_model/llama.py
mblt_model_zoo/transformers/large_language_model/qwen2.py
mblt_model_zoo/transformers/speech_to_text/__init__.py
mblt_model_zoo/transformers/speech_to_text/whisper.py
mblt_model_zoo/transformers/text_to_speech/__init__.py
mblt_model_zoo/transformers/utils/__init__.py
mblt_model_zoo/transformers/utils/_api.py
mblt_model_zoo/transformers/utils/auto.py
mblt_model_zoo/transformers/utils/benchmark_utils.py
mblt_model_zoo/transformers/utils/cache_utils.py
mblt_model_zoo/transformers/utils/generation_utils.py
mblt_model_zoo/transformers/utils/types.py
mblt_model_zoo/transformers/vision_language_model/__init__.py
mblt_model_zoo/transformers/vision_language_model/aya_vision.py
mblt_model_zoo/transformers/vision_language_model/blip.py
mblt_model_zoo/transformers/vision_language_model/qwen2_vl.py
mblt_model_zoo/utils/__init__.py
mblt_model_zoo/utils/downloads.py
mblt_model_zoo/utils/logging.py
mblt_model_zoo/vision/__init__.py
mblt_model_zoo/vision/_api.py
mblt_model_zoo/vision/wrapper.py
mblt_model_zoo/vision/face_detection/__init__.py
mblt_model_zoo/vision/image_classification/__init__.py
mblt_model_zoo/vision/image_classification/alexnet.py
mblt_model_zoo/vision/image_classification/convnext.py
mblt_model_zoo/vision/image_classification/deit.py
mblt_model_zoo/vision/image_classification/deit3.py
mblt_model_zoo/vision/image_classification/densenet.py
mblt_model_zoo/vision/image_classification/flexivit.py
mblt_model_zoo-0.5.0.dist-info/licenses/LICENSE
mblt_model_zoo-0.5.0.dist-info/METADATA
mblt_model_zoo-0.5.0.dist-info/WHEEL
mblt_model_zoo-0.5.0.dist-info/entry_points.txt
mblt_model_zoo-0.5.0.dist-info/top_level.txt
mblt_model_zoo-0.5.0.dist-info/RECORD
