Metadata-Version: 2.4
Name: mblt-model-zoo
Version: 0.5.0
Summary: A collection of pre-quantized AI models for Mobilint NPUs.
Author-email: "Mobilint Inc." <tech-support@mobilint.com>
License: BSD-3-Clause
Project-URL: Home, https://www.mobilint.com/
Project-URL: Repository, https://github.com/mobilint/mblt-model-zoo
Keywords: quantization,NPU,model zoo,pre-quantized models,inference,mobilint,mblt,aries
Classifier: Development Status :: 2 - Pre-Alpha
Classifier: Environment :: Console
Classifier: Intended Audience :: Developers
Classifier: Intended Audience :: Education
Classifier: Intended Audience :: Science/Research
Classifier: Intended Audience :: System Administrators
Classifier: License :: OSI Approved :: BSD License
Classifier: Operating System :: Microsoft :: Windows
Classifier: Operating System :: POSIX :: Linux
Classifier: Programming Language :: Python :: 3
Classifier: Programming Language :: Python :: 3.8
Classifier: Programming Language :: Python :: 3.9
Classifier: Programming Language :: Python :: 3.10
Classifier: Programming Language :: Python :: 3.11
Classifier: Programming Language :: Python :: 3.12
Classifier: Topic :: Scientific/Engineering
Classifier: Topic :: Scientific/Engineering :: Artificial Intelligence
Classifier: Topic :: Software Development
Classifier: Topic :: Software Development :: Libraries
Classifier: Topic :: Software Development :: Libraries :: Python Modules
Requires-Python: <3.13,>=3.9
License-File: LICENSE
Requires-Dist: maccel<=0.30.1,>=0.29.0
Requires-Dist: numpy>=1.26.0
Requires-Dist: torch>=2.4.1
Requires-Dist: opencv-python>=4.11.0.86
Requires-Dist: pillow>=11.1.0
Requires-Dist: setuptools>=70.0.0
Requires-Dist: tqdm
Requires-Dist: wheel
Provides-Extra: transformers
Requires-Dist: transformers<=4.57.1,>=4.54.0; extra == "transformers"
Requires-Dist: matplotlib; extra == "transformers"
Dynamic: license-file
